isage_data-0.2.3.0.dist-info/licenses/LICENSE
sage/data/__init__.py
sage/data/cli.py
sage/data/manager.py
sage/data/sources/__init__.py
sage/data/sources/agent_benchmark/__init__.py
sage/data/sources/agent_benchmark/dataloader.py
sage/data/sources/agent_benchmark/dataset.yaml
sage/data/sources/agent_benchmark/fix_tool_references.py
sage/data/sources/agent_benchmark/generate_data.py
sage/data/sources/agent_benchmark/prepare_planning_data.py
sage/data/sources/agent_benchmark/prepare_runtime_data.py
sage/data/sources/agent_benchmark/prepare_timing_data.py
sage/data/sources/agent_benchmark/sync_runtime_data.py
sage/data/sources/agent_benchmark/test_integration.py
sage/data/sources/agent_benchmark/validate_cross_task.py
sage/data/sources/agent_benchmark/validate_data.py
sage/data/sources/agent_benchmark/external_benchmarks/__init__.py
sage/data/sources/agent_benchmark/external_benchmarks/convert_apibank_dialogues.py
sage/data/sources/agent_benchmark/external_benchmarks/convert_bfcl_correct.py
sage/data/sources/agent_benchmark/external_benchmarks/converters.py
sage/data/sources/agent_benchmark/external_benchmarks/download_all.py
sage/data/sources/agent_benchmark/external_benchmarks/download_apibank.py
sage/data/sources/agent_benchmark/external_benchmarks/download_bfcl.py
sage/data/sources/agent_benchmark/external_benchmarks/download_toolalpaca.py
sage/data/sources/agent_benchmark/external_benchmarks/download_toolbench.py
sage/data/sources/agent_benchmark/external_benchmarks/loader.py
sage/data/sources/agent_benchmark/external_benchmarks/merge_bfcl_to_splits.py
sage/data/sources/agent_benchmark/tests/test_agent_benchmark_loader.py
sage/data/sources/agent_sft/__init__.py
sage/data/sources/agent_sft/dataloader.py
sage/data/sources/agent_sft/dataset.yaml
sage/data/sources/agent_sft/fix_tool_ids.py
sage/data/sources/agent_sft/schemas.py
sage/data/sources/agent_sft/data/generate_data.py
sage/data/sources/agent_sft/data/prompts_template.yaml
sage/data/sources/agent_sft/tests/test_agent_sft_loader.py
isage_data-0.2.3.0.dist-info/METADATA
isage_data-0.2.3.0.dist-info/WHEEL
isage_data-0.2.3.0.dist-info/entry_points.txt
isage_data-0.2.3.0.dist-info/top_level.txt
isage_data-0.2.3.0.dist-info/RECORD
