Metadata-Version: 2.4
Name: isage-data
Version: 0.2.3.0
Summary: SAGE Data - Unified data loaders for memory benchmark datasets (LongMemEval, Locomo, MemAgentBench, etc.)
Author-email: IntelliStream Team <shuhao_zhang@hust.edu.cn>
License: MIT
Project-URL: Homepage, https://github.com/intellistream/sageData
Project-URL: Repository, https://github.com/intellistream/sageData
Project-URL: Documentation, https://github.com/intellistream/sageData/blob/main/README.md
Project-URL: Issues, https://github.com/intellistream/sageData/issues
Keywords: dataset,benchmark,memory,ai,longmemeval,locomo,memagentbench,sage
Classifier: Development Status :: 3 - Alpha
Classifier: Intended Audience :: Developers
Classifier: Intended Audience :: Science/Research
Classifier: License :: OSI Approved :: MIT License
Classifier: Programming Language :: Python :: 3
Classifier: Programming Language :: Python :: 3.10
Classifier: Programming Language :: Python :: 3.11
Classifier: Programming Language :: Python :: 3.12
Classifier: Topic :: Scientific/Engineering :: Artificial Intelligence
Classifier: Topic :: Software Development :: Libraries :: Python Modules
Requires-Python: >=3.10
License-File: LICENSE
Requires-Dist: isage-common>=0.2.0
Requires-Dist: pandas>=2.0.0
Requires-Dist: numpy<2.3.0,>=1.26.0
Requires-Dist: pyyaml>=6.0
Requires-Dist: datasets>=2.14.0
Requires-Dist: pyarrow<18.0.0,>=10.0.0
Provides-Extra: dev
Requires-Dist: pytest>=7.0.0; extra == "dev"
Requires-Dist: ruff>=0.1.0; extra == "dev"
Requires-Dist: mypy>=1.0.0; extra == "dev"
Requires-Dist: detect-secrets>=1.5.0; extra == "dev"
Requires-Dist: pre-commit>=2.20.0; extra == "dev"
Dynamic: license-file
